irckaaja/__init__.py
irckaaja/botscript.py
irckaaja/channel.py
irckaaja/client.py
irckaaja/config.py
irckaaja/connection.py
irckaaja/dynamicmodule.py
irckaaja/irckaaja.py
irckaaja/protocol.py
irckaaja/scripts/__init__.py
irckaaja/scripts/helloworld.py
irckaaja/scripts/irclinkhistory.py
irckaaja/scripts/moduleloader.py
irckaaja/scripts/urls.py
irckaaja/scripts/youtubeannouncer.py
irckaaja-0.3.0.dist-info/METADATA
irckaaja-0.3.0.dist-info/WHEEL
irckaaja-0.3.0.dist-info/RECORD
