Metadata-Version: 2.1
Name: irckaaja
Version: 0.3.0
Summary: 
Author: Jukka-Pekka Virtanen
Author-email: virtanen@jukk.is
Requires-Python: >=3.9,<4.0
Classifier: Programming Language :: Python :: 3
Classifier: Programming Language :: Python :: 3.9
Classifier: Programming Language :: Python :: 3.10
Classifier: Programming Language :: Python :: 3.11
Requires-Dist: configobj
